pywavers-0.1.0.dist-info/METADATA
pywavers-0.1.0.dist-info/WHEEL
pywavers-0.1.0.dist-info/license_files/LICENSE
pywavers/test_resources/one_channel_f64.wav
pywavers/test_resources/one_channel_i32.wav
pywavers/test_resources/one_channel_i16.wav
pywavers/test_resources/one_channel_f32.wav
pywavers/__init__.py
pywavers/wavers.py
pywavers/pywavers.cpython-311-x86_64-linux-gnu.so
pywavers-0.1.0.dist-info/RECORD
