Metadata-Version: 2.3
Name: pywavers
Version: 0.1.0
Requires-Dist: numpy >=1.21
Requires-Dist: soundfile >=0.10 ; extra == 'test'
Provides-Extra: test
License-File: LICENSE
Summary: A mixed Rust and Python crate/package for reading and writing WAVE files. Exposes the Rust crate Wavers to Python.
Author: Jack Geraghty (jmg049)
License: MIT
Requires-Python: >=3.10
Project-URL: Source Code, https://github.com/jmg049/PyWavers/
